aroay_cloudscraper/__init__.py
aroay_cloudscraper/__version__.py
aroay_cloudscraper/downloadermiddlewares.py
aroay_cloudscraper/request.py
aroay_cloudscraper/settings.py
aroay_cloudscraper-1.5.dist-info/LICENSE
aroay_cloudscraper-1.5.dist-info/METADATA
aroay_cloudscraper-1.5.dist-info/WHEEL
aroay_cloudscraper-1.5.dist-info/top_level.txt
aroay_cloudscraper-1.5.dist-info/RECORD
