Metadata-Version: 2.1
Name: aroay-cloudscraper
Version: 1.5
Summary: scrapy的一个下载中间件，绕过cloudflare检测
Home-page: https://github.com/hwpchn/AroayCloudScraper.git
Author: hwpchn
Author-email: 13692839895@163.com
License: UNKNOWN
Platform: UNKNOWN
Classifier: Programming Language :: Python :: 3
Classifier: License :: OSI Approved :: MIT License
Requires-Dist: cloudscraper (>=1.2.58)
Requires-Dist: scrapy (>=2.0.0)
